setup.cfg
setup.py
typeopt/__init__.py
typeopt/arguments.py
typeopt/parsing.py
typeopt.egg-info/PKG-INFO
typeopt.egg-info/SOURCES.txt
typeopt.egg-info/dependency_links.txt
typeopt.egg-info/not-zip-safe
typeopt.egg-info/requires.txt
typeopt.egg-info/top_level.txt