Metadata-Version: 1.1
Name: typeopt
Version: 0.2
Summary: Typed docopt
Home-page: https://github.com/1o0ko/typeopt
Author: Wojciech Stokowiec
Author-email: wojciech.stokowiec@tooploox.com
License: UNKNOWN
Download-URL: https://github.com/1o0ko/typeopt/tarball/0.1
Keywords: arguments,docopt,command-line
Platform: UNKNOWN
